Kreate-0.0.2.data/data/dependency_model/dependency_model.pkl
Kreate-0.0.2.data/scripts/kreate
Kreate-0.0.2.data/scripts/kreate.bat
Kreate-0.0.2.dist-info/DESCRIPTION.rst
Kreate-0.0.2.dist-info/LICENSE.txt
Kreate-0.0.2.dist-info/METADATA
Kreate-0.0.2.dist-info/RECORD
Kreate-0.0.2.dist-info/WHEEL
Kreate-0.0.2.dist-info/metadata.json
Kreate-0.0.2.dist-info/top_level.txt
kreate/__init__.py
kreate/__main__.py
kreate/chart_model.py
kreate/codefinder.py
kreate/dependencies.py
kreate/dependency_stopwords.py
kreate/handler.py
kreate/helm.py
kreate/model_scorer.py
