Metadata-Version: 2.0
Name: Kreate
Version: 0.0.2
Summary: Fast deployment of dependencies to Kubernetes
Home-page: http://pypi.python.org/pypi/Kreate/
Author: Yaron Schneider, Limor Lahiani, Tomer Rosenthal, Emre Kenci
Author-email: torosent@microsoft.com
License: UNKNOWN
Platform: UNKNOWN
Requires-Dist: gitpython
Requires-Dist: knack
Requires-Dist: numpy
Requires-Dist: scipy
Requires-Dist: nltk
Requires-Dist: sklearn
Requires-Dist: jellyfish
Requires-Dist: pyyaml
Provides-Extra: test
Requires-Dist: pytest; extra == 'test'
